stac_fastapi/types/__init__.py
stac_fastapi/types/config.py
stac_fastapi/types/conformance.py
stac_fastapi/types/core.py
stac_fastapi/types/errors.py
stac_fastapi/types/extension.py
stac_fastapi/types/links.py
stac_fastapi/types/py.typed
stac_fastapi/types/requests.py
stac_fastapi/types/rfc3339.py
stac_fastapi/types/search.py
stac_fastapi/types/stac.py
stac_fastapi/types/version.py
stac_fastapi_types-6.2.0.dist-info/METADATA
stac_fastapi_types-6.2.0.dist-info/WHEEL
stac_fastapi_types-6.2.0.dist-info/RECORD
